groupdocs_translation_cloud/__init__.py
groupdocs_translation_cloud/api_client.py
groupdocs_translation_cloud/api_response.py
groupdocs_translation_cloud/configuration.py
groupdocs_translation_cloud/exceptions.py
groupdocs_translation_cloud/py.typed
groupdocs_translation_cloud/rest.py
groupdocs_translation_cloud/api/__init__.py
groupdocs_translation_cloud/api/file_api.py
groupdocs_translation_cloud/api/swagger_api.py
groupdocs_translation_cloud/api/translation_api.py
groupdocs_translation_cloud/models/__init__.py
groupdocs_translation_cloud/models/api_enums.py
groupdocs_translation_cloud/models/cloud_file_request.py
groupdocs_translation_cloud/models/cloud_file_response.py
groupdocs_translation_cloud/models/cloud_file_response_with_additional_info.py
groupdocs_translation_cloud/models/cloud_hugo_response.py
groupdocs_translation_cloud/models/cloud_text_response.py
groupdocs_translation_cloud/models/csv_file_request.py
groupdocs_translation_cloud/models/file_request.py
groupdocs_translation_cloud/models/health_check_entity.py
groupdocs_translation_cloud/models/health_check_status.py
groupdocs_translation_cloud/models/html_file_request.py
groupdocs_translation_cloud/models/http_status_code.py
groupdocs_translation_cloud/models/hugo_request.py
groupdocs_translation_cloud/models/image_to_file_request.py
groupdocs_translation_cloud/models/image_to_text_request.py
groupdocs_translation_cloud/models/language_pair_data.py
groupdocs_translation_cloud/models/markdown_file_request.py
groupdocs_translation_cloud/models/media_to_file_request.py
groupdocs_translation_cloud/models/media_to_text_request.py
groupdocs_translation_cloud/models/pdf_file_request.py
groupdocs_translation_cloud/models/presentation_file_request.py
groupdocs_translation_cloud/models/spreadsheet_file_request.py
groupdocs_translation_cloud/models/srt_file_request.py
groupdocs_translation_cloud/models/status_response.py
groupdocs_translation_cloud/models/string_string_tuple.py
groupdocs_translation_cloud-25.6.0.dist-info/METADATA
groupdocs_translation_cloud-25.6.0.dist-info/WHEEL
groupdocs_translation_cloud-25.6.0.dist-info/top_level.txt
groupdocs_translation_cloud-25.6.0.dist-info/RECORD
