Metadata-Version: 2.1
Name: groupdocs-translation-cloud
Version: 25.6.0
Summary: GroupDocs.Translation SDK
Home-page: 
Author: GroupDocs
Author-email: anton.perhunov@aspose.com
License: MIT
Keywords: OpenAPI,OpenAPI-Generator,GroupDocs.Translation SDK
Requires-Dist: urllib3<2.1.0,>=1.25.3
Requires-Dist: python-dateutil
Requires-Dist: pydantic>=2
Requires-Dist: typing-extensions>=4.7.1
